[
  {
    "id": null,
    "tags": null,
    "type": "Description",
    "title": null,
    "stem": {
      "format": "moodle",
      "text": "U6 p60 Listening Audio1 You will hear people talking in eight different situations. First, identify the key words in the question below. Then listen and choose the best answer. https)//serge.bibauw.be/teaching/english5/gold_b2_cb_18_u6_p60_listening.mp3"
    },
    "hasEmbeddedAnswers": false
  },
  {
    "type": "MC",
    "title": null,
    "stem": {
      "format": "moodle",
      "text": "U6 p60 Listening 1.1 You hear a woman talking about a play. What did she dislike about it?"
    },
    "hasEmbeddedAnswers": false,
    "globalFeedback": null,
    "choices": [
      {
        "isCorrect": true,
        "weight": null,
        "text": {
          "format": "moodle",
          "text": "the lighting"
        },
        "feedback": null
      },
      {
        "isCorrect": false,
        "weight": null,
        "text": {
          "format": "moodle",
          "text": "the music"
        },
        "feedback": null
      },
      {
        "isCorrect": false,
        "weight": null,
        "text": {
          "format": "moodle",
          "text": "the costumes"
        },
        "feedback": null
      }
    ],
    "id": null,
    "tags": null
  },
  {
    "id": null,
    "tags": null,
    "type": "Description",
    "title": null,
    "stem": {
      "format": "moodle",
      "text": "U6 p60 Listening Audio2 Identify the key words in the following questions. Then listen and choose the best answer. https)//serge.bibauw.be/teaching/english5/gold_b2_cb_19_u6_p60_listening.mp3"
    },
    "hasEmbeddedAnswers": false
  },
  {
    "type": "MC",
    "title": null,
    "stem": {
      "format": "moodle",
      "text": "U6 p60 Listening 3.2 You hear a man and a woman talking about a visit to the theatre. How does the woman feel about the arrangements?"
    },
    "hasEmbeddedAnswers": false,
    "globalFeedback": null,
    "choices": [
      {
        "isCorrect": false,
        "weight": null,
        "text": {
          "format": "moodle",
          "text": "annoyed that the play finishes so late"
        },
        "feedback": null
      },
      {
        "isCorrect": true,
        "weight": null,
        "text": {
          "format": "moodle",
          "text": "worried about when they’re going to eat"
        },
        "feedback": null
      },
      {
        "isCorrect": false,
        "weight": null,
        "text": {
          "format": "moodle",
          "text": "confused about what time the play starts"
        },
        "feedback": null
      }
    ],
    "id": null,
    "tags": null
  },
  {
    "type": "MC",
    "title": null,
    "stem": {
      "format": "moodle",
      "text": "U6 p60 Listening 3.3 You hear part of a radio programme. What kind of programme is it?"
    },
    "hasEmbeddedAnswers": false,
    "globalFeedback": null,
    "choices": [
      {
        "isCorrect": false,
        "weight": null,
        "text": {
          "format": "moodle",
          "text": "a celebrity interview"
        },
        "feedback": null
      },
      {
        "isCorrect": false,
        "weight": null,
        "text": {
          "format": "moodle",
          "text": "a film review"
        },
        "feedback": null
      },
      {
        "isCorrect": true,
        "weight": null,
        "text": {
          "format": "moodle",
          "text": "a news show"
        },
        "feedback": null
      }
    ],
    "id": null,
    "tags": null
  },
  {
    "type": "MC",
    "title": null,
    "stem": {
      "format": "moodle",
      "text": "U6 p60 Listening 3.4 You hear a woman giving some information on the radio about a comedy festival. Why is it going to be different this year?"
    },
    "hasEmbeddedAnswers": false,
    "globalFeedback": null,
    "choices": [
      {
        "isCorrect": false,
        "weight": null,
        "text": {
          "format": "moodle",
          "text": "The tickets will be more expensive."
        },
        "feedback": null
      },
      {
        "isCorrect": false,
        "weight": null,
        "text": {
          "format": "moodle",
          "text": "It will be held in a smaller venue."
        },
        "feedback": null
      },
      {
        "isCorrect": true,
        "weight": null,
        "text": {
          "format": "moodle",
          "text": "It will be on different dates."
        },
        "feedback": null
      }
    ],
    "id": null,
    "tags": null
  },
  {
    "type": "MC",
    "title": null,
    "stem": {
      "format": "moodle",
      "text": "U6 p60 Listening 3.5 You hear a man interviewing a ballet dancer on the radio. Why has she decided to retire later this year?"
    },
    "hasEmbeddedAnswers": false,
    "globalFeedback": null,
    "choices": [
      {
        "isCorrect": false,
        "weight": null,
        "text": {
          "format": "moodle",
          "text": "She is worried about getting injured."
        },
        "feedback": null
      },
      {
        "isCorrect": false,
        "weight": null,
        "text": {
          "format": "moodle",
          "text": "She no longer enjoys performing."
        },
        "feedback": null
      },
      {
        "isCorrect": true,
        "weight": null,
        "text": {
          "format": "moodle",
          "text": "She wants to make her family the priority."
        },
        "feedback": null
      }
    ],
    "id": null,
    "tags": null
  },
  {
    "type": "MC",
    "title": null,
    "stem": {
      "format": "moodle",
      "text": "U6 p60 Listening 3.6 You hear a man and a woman talking on the radio about a new art exhibition. What do they agree is special about it?"
    },
    "hasEmbeddedAnswers": false,
    "globalFeedback": null,
    "choices": [
      {
        "isCorrect": true,
        "weight": null,
        "text": {
          "format": "moodle",
          "text": "the variety of genres"
        },
        "feedback": null
      },
      {
        "isCorrect": false,
        "weight": null,
        "text": {
          "format": "moodle",
          "text": "the unusual location"
        },
        "feedback": null
      },
      {
        "isCorrect": false,
        "weight": null,
        "text": {
          "format": "moodle",
          "text": "the famous artists"
        },
        "feedback": null
      }
    ],
    "id": null,
    "tags": null
  },
  {
    "type": "MC",
    "title": null,
    "stem": {
      "format": "moodle",
      "text": "U6 p60 Listening 3.7 You hear an actress being interviewed on the radio. What is she doing?"
    },
    "hasEmbeddedAnswers": false,
    "globalFeedback": null,
    "choices": [
      {
        "isCorrect": true,
        "weight": null,
        "text": {
          "format": "moodle",
          "text": "giving her opinion about the topic of the play"
        },
        "feedback": null
      },
      {
        "isCorrect": false,
        "weight": null,
        "text": {
          "format": "moodle",
          "text": "describing her relationship with the director"
        },
        "feedback": null
      },
      {
        "isCorrect": false,
        "weight": null,
        "text": {
          "format": "moodle",
          "text": "stating a wish to direct a play herself"
        },
        "feedback": null
      }
    ],
    "id": null,
    "tags": null
  },
  {
    "type": "MC",
    "title": null,
    "stem": {
      "format": "moodle",
      "text": "U6 p60 Listening 3.8 You hear a man and a woman talking. Who is the man?"
    },
    "hasEmbeddedAnswers": false,
    "globalFeedback": null,
    "choices": [
      {
        "isCorrect": false,
        "weight": null,
        "text": {
          "format": "moodle",
          "text": "her brother"
        },
        "feedback": null
      },
      {
        "isCorrect": false,
        "weight": null,
        "text": {
          "format": "moodle",
          "text": "her teacher"
        },
        "feedback": null
      },
      {
        "isCorrect": true,
        "weight": null,
        "text": {
          "format": "moodle",
          "text": "her friend"
        },
        "feedback": null
      }
    ],
    "id": null,
    "tags": null
  }
]